{
  "tasks": [
    {
      "value": "vite",
      "completed": false,
      "id": 10
    },
    {
      "value": "h",
      "completed": false,
      "id": 11
    },
    {
      "value": "f",
      "completed": false,
      "id": 12
    },
    {
      "value": "f",
      "completed": false,
      "id": 13
    },
    {
      "value": "y",
      "completed": true,
      "id": 14
    },
    {
      "value": "h",
      "completed": true,
      "id": 15
    },
    {
      "value": "d",
      "completed": true,
      "id": 16
    },
    {
      "value": "d",
      "completed": true,
      "id": 17
    },
    {
      "value": "gg",
      "completed": true,
      "id": 18
    }
  ]
}